kafka_avro_helper/__init__.py
kafka_avro_helper/consumer.py
kafka_avro_helper/logger.py
kafka_avro_helper/producer.py
kafka_avro_helper/validate.py
tests/__init__.py
tests/consumer.py
tests/producer.py
tests/slow_qraphql_operation_detected.py
tests/user_feedback.py
kafka_avro_helper-0.1.9.dist-info/LICENSE
kafka_avro_helper-0.1.9.dist-info/METADATA
kafka_avro_helper-0.1.9.dist-info/WHEEL
kafka_avro_helper-0.1.9.dist-info/top_level.txt
kafka_avro_helper-0.1.9.dist-info/RECORD
